Workbook

Sheet Summary
A1: NL-Groww golden set: hand labels vs AI tags (first pass)
A2: 27 comments sampled across themes, sources, languages and guardrail cases. GS01-GS02 were walked through with Claude as practice items and are excluded from scoring. Labelled by the project owner on 31 Oct 2026 without seeing the AI tags. AI tags: Gemini Lite, prompt v1.2.
A4: Measure | B4: Matches | C4: Items scored | D4: Agreement
A5: Relevant? | B5: =SUMPRODUCT((Items!$B$2:$B$28="No")*Items!O2:O28) -> 14 | C5: =COUNTIF(Items!$B$2:$B$28,"No") -> 25 | D5: =IF(C5=0,"",B5/C5) -> 0.56
A6: Main event | B6: =SUMPRODUCT((Items!$B$2:$B$28="No")*Items!P2:P28) -> 14 | C6: =COUNTIF(Items!$B$2:$B$28,"No") -> 25 | D6: =IF(C6=0,"",B6/C6) -> 0.56
A7: Drop-off type | B7: =SUMPRODUCT((Items!$B$2:$B$28="No")*Items!Q2:Q28) -> 18 | C7: =COUNTIF(Items!$B$2:$B$28,"No") -> 25 | D7: =IF(C7=0,"",B7/C7) -> 0.72
A8: Main reason | B8: =SUMPRODUCT((Items!$B$2:$B$28="No")*Items!R2:R28) -> 13 | C8: =COUNTIF(Items!$B$2:$B$28,"No") -> 25 | D8: =IF(C8=0,"",B8/C8) -> 0.52
A9: Overall (all 4 fields) | B9: =SUM(B5:B8) -> 59 | C9: =SUM(C5:C8) -> 100 | D9: =IF(C9=0,"",B9/C9) -> 0.59
A11: AI guardrail violations on these 27 (fund names or advice in the AI's own fields) | D11: =COUNTIF(Items!S2:S28,"VIOLATION*") -> 0
A12: Rules: event and reason count as a match if the labeller's choice is among the AI's tags (the AI can tag several).
A14: What the disagreements show
A15: All relevance disagreements are AI = relevant, labeller = not relevant. Most are forum replies, staff answers, regulatory questions and general opinions (TradingQnA, Zerodha Varsity): the AI's relevance filter is too generous for forum text.
A16: A few relevance 'No' labels (GS22, GS23, GS26) are first-person questions or needs that the codebook counts as relevant: definition-boundary cases, listed as review candidates.
A17: Event and reason gaps are mostly cases where two readings fit (skipped vs payment failed; intention to withdraw vs withdrew) or the AI tagged secondary reasons the labeller left out.
A18: Robustness check (see sheet): removing forum sources leaves the headline findings unchanged, so the looser relevance filter inflates volume, not the conclusions.

Sheet Items
A1: ID | B1: Practice item? | C1: Stratum | D1: Source | E1: Comment | F1: Labeller: relevant | G1: Labeller: event | H1: Labeller: drop-off | I1: Labeller: reason | J1: Labeller note | K1: AI: relevant | L1: AI: events (all) | M1: AI: drop-off | N1: AI: reasons (all) | O1: Relevant match | P1: Event match | Q1: Drop-off match | R1: Reason match | S1: AI guardrail check
A2: GS01 | B2: Yes | C2: not relevant (AI) | D2: app store | E2: External Mutual Funds. App is excellent, but from last2 months the external Mutual Funds are not getting updated | F2: yes | G2: checked_tracked | H2: none | I2: app_friction_or_bug | K2: no | L2: |none| | M2: none | N2: |none| | O2: =IF(F2=K2,1,0) -> 0 | P2: =IF(OR(ISNUMBER(SEARCH("|"&G2&"|",L2)),AND(G2="none",OR(L2="|none|",L2=""))),1,0) -> 0 | Q2: =IF(H2=M2,1,0) -> 1 | R2: =IF(OR(ISNUMBER(SEARCH("|"&I2&"|",N2)),AND(I2="none",OR(N2="|none|",N2=""))),1,0) -> 0 | S2: pass
A3: GS02 | B3: Yes | C3: not relevant (AI) | D3: play store | E3: My very first experience is worst experience, below is the reason. I bid for "Indian Railway Finance corporation limited" where the payment can be done only by UPI. So, I entered my phonePe UPI details, and i haven't received any UPI Mandate in the next 60 minutes. I unable to bid because the bid time was closed. Very bad experience will switch a better app. | F3: no | G3: none | H3: none | I3: none | K3: no | L3: |none| | M3: none | N3: |none| | O3: =IF(F3=K3,1,0) -> 1 | P3: =IF(OR(ISNUMBER(SEARCH("|"&G3&"|",L3)),AND(G3="none",OR(L3="|none|",L3=""))),1,0) -> 1 | Q3: =IF(H3=M3,1,0) -> 1 | R3: =IF(OR(ISNUMBER(SEARCH("|"&I3&"|",N3)),AND(I3="none",OR(N3="|none|",N3=""))),1,0) -> 1 | S3: pass
A4: GS03 | B4: No | C4: not relevant (AI) | D4: tradingqna | E4: CoolBird: Here you go. Care to share yours? image 762×420 15.1 KB Nifty index fund is just for comparision. | F4: no | G4: none | H4: none | I4: none | K4: no | L4: |none| | M4: none | N4: |none| | O4: =IF(F4=K4,1,0) -> 1 | P4: =IF(OR(ISNUMBER(SEARCH("|"&G4&"|",L4)),AND(G4="none",OR(L4="|none|",L4=""))),1,0) -> 1 | Q4: =IF(H4=M4,1,0) -> 1 | R4: =IF(OR(ISNUMBER(SEARCH("|"&I4&"|",N4)),AND(I4="none",OR(N4="|none|",N4=""))),1,0) -> 1 | S4: pass
A5: GS04 | B5: No | C5: failed payment / mandate | D5: app store | E5: I missed my SIP payment !. I’m really disappointed at this app. I pay SIP per month but for some reason this month, all my SIPs couldn’t get processed because of some network error or technical issues from banks end but I couldn’t even repeat the payment because paytm money showed the payments were in progress the second time when I tried paying again! This is disappointing because now I have to pay in lumpsum (which I can’t)! And just like that, my sip for this month has been missed. I did not even log in to my net banking account so I did not even process my payment but payment in progress left me with no option but to wait for next month! | F5: yes | G5: lapsed_failed_payment | H5: involuntary | I5: payment_mandate_failure | K5: yes | L5: |skipped| | M5: involuntary | N5: |payment_mandate_failure|app_friction_or_bug| | O5: =IF(F5=K5,1,0) -> 1 | P5: =IF(OR(ISNUMBER(SEARCH("|"&G5&"|",L5)),AND(G5="none",OR(L5="|none|",L5=""))),1,0) -> 0 | Q5: =IF(H5=M5,1,0) -> 1 | R5: =IF(OR(ISNUMBER(SEARCH("|"&I5&"|",N5)),AND(I5="none",OR(N5="|none|",N5=""))),1,0) -> 1 | S5: pass
A6: GS05 | B6: No | C6: failed payment / mandate | D6: play store | E6: I started sip last month and this month second installment deducted bt after someday I have got massage that ur second installment was rejected . So what is going to happening. If amount was deducted so where is my money when it well refund me. I trie to call customer care but not able to contact .. ☹️☹️, Why u were not able to contact to me My phone is one u can call my another , I tried to contact u Bt not able to contact with u... | F6: yes | G6: lapsed_failed_payment | H6: none | I6: trust_or_support_failure | K6: yes | L6: |started|lapsed_failed_payment| | M6: involuntary | N6: |payment_mandate_failure|trust_or_support_failure| | O6: =IF(F6=K6,1,0) -> 1 | P6: =IF(OR(ISNUMBER(SEARCH("|"&G6&"|",L6)),AND(G6="none",OR(L6="|none|",L6=""))),1,0) -> 1 | Q6: =IF(H6=M6,1,0) -> 0 | R6: =IF(OR(ISNUMBER(SEARCH("|"&I6&"|",N6)),AND(I6="none",OR(N6="|none|",N6=""))),1,0) -> 1 | S6: pass
A7: GS06 | B7: No | C7: failed payment / mandate | D7: tradingqna | E7: Yes, the order will fail if the units are pledged in the backend. FYI soon we will start should the number of units pledged for mf | F7: no | G7: none | H7: none | I7: none | K7: yes | L7: |lapsed_failed_payment| | M7: involuntary | N7: |payment_mandate_failure| | O7: =IF(F7=K7,1,0) -> 0 | P7: =IF(OR(ISNUMBER(SEARCH("|"&G7&"|",L7)),AND(G7="none",OR(L7="|none|",L7=""))),1,0) -> 0 | Q7: =IF(H7=M7,1,0) -> 0 | R7: =IF(OR(ISNUMBER(SEARCH("|"&I7&"|",N7)),AND(I7="none",OR(N7="|none|",N7=""))),1,0) -> 0 | S7: pass
A8: GS07 | B8: No | C8: voluntary stop/skip/pause | D8: play store | E8: Please correct the mention thing. 1 - when we start SIP, why we give compulsary initial investment amount. You give this on option, why compulsary. 2 - No option or choose SIP date. 3 - Add option for choose favourite. Bcz of this i stop using this app. When you correct this i will start using this again. Thankyou. | F8: yes | G8: none | H8: none | I8: missing_control_pause_skip_modify | J8: The user didn't even started the SIP due to App features so here acquisition itself failed. That's why choose none of these for 2nd and 3rd | K8: yes | L8: |stopped_cancelled| | M8: voluntary | N8: |app_friction_or_bug|missing_control_pause_skip_modify| | O8: =IF(F8=K8,1,0) -> 1 | P8: =IF(OR(ISNUMBER(SEARCH("|"&G8&"|",L8)),AND(G8="none",OR(L8="|none|",L8=""))),1,0) -> 0 | Q8: =IF(H8=M8,1,0) -> 0 | R8: =IF(OR(ISNUMBER(SEARCH("|"&I8&"|",N8)),AND(I8="none",OR(N8="|none|",N8=""))),1,0) -> 1 | S8: pass
A9: GS08 | B9: No | C9: voluntary stop/skip/pause | D9: app store | E9: deceptive and fraud behaviour. unable to cancel my mutual fund SIP for last 2 weeks. The cancellation process goes through and their is confirmation on the app but the cancellation doesn’t happen and there is no email confirmation. also customer care calls get disconnected and there is no other way to reach these folks. | F9: yes | G9: stopped_cancelled | H9: voluntary | I9: none | K9: yes | L9: |stopped_cancelled| | M9: voluntary | N9: |app_friction_or_bug|trust_or_support_failure| | O9: =IF(F9=K9,1,0) -> 1 | P9: =IF(OR(ISNUMBER(SEARCH("|"&G9&"|",L9)),AND(G9="none",OR(L9="|none|",L9=""))),1,0) -> 1 | Q9: =IF(H9=M9,1,0) -> 1 | R9: =IF(OR(ISNUMBER(SEARCH("|"&I9&"|",N9)),AND(I9="none",OR(N9="|none|",N9=""))),1,0) -> 0 | S9: pass
A10: GS09 | B10: No | C10: voluntary stop/skip/pause | D10: tradingqna | E10: SIP is a good technique to buy into a MF or a direct EQ portfolio. However, a single stop SIP can be quite dangerous as you would be putting in all your money in a single stock. Please do check out this chapter, particularly on unsystematic risk - http://zerodha.com/varsity/chapter/risk-part-1/ | F10: no | G10: none | H10: none | I10: none | K10: yes | L10: |stopped_cancelled| | M10: voluntary | N10: |other| | O10: =IF(F10=K10,1,0) -> 0 | P10: =IF(OR(ISNUMBER(SEARCH("|"&G10&"|",L10)),AND(G10="none",OR(L10="|none|",L10=""))),1,0) -> 0 | Q10: =IF(H10=M10,1,0) -> 0 | R10: =IF(OR(ISNUMBER(SEARCH("|"&I10&"|",N10)),AND(I10="none",OR(N10="|none|",N10=""))),1,0) -> 0 | S10: pass
A11: GS10 | B11: No | C11: missing pause/skip control | D11: play store | E11: Hello dear groww, Could you please add "SIP pause" and "amount & date modify " option in groww app. it will very helpful for us. As i see zerodha given these option to his customer but in groww we do not have these option. So can we expect groww will update this option and We will get this option as soon as possible. Thanks | F11: yes | G11: switched_platform | H11: none | I11: missing_control_pause_skip_modify | K11: yes | L11: |none| | M11: none | N11: |missing_control_pause_skip_modify| | O11: =IF(F11=K11,1,0) -> 1 | P11: =IF(OR(ISNUMBER(SEARCH("|"&G11&"|",L11)),AND(G11="none",OR(L11="|none|",L11=""))),1,0) -> 0 | Q11: =IF(H11=M11,1,0) -> 1 | R11: =IF(OR(ISNUMBER(SEARCH("|"&I11&"|",N11)),AND(I11="none",OR(N11="|none|",N11=""))),1,0) -> 1 | S11: pass
A12: GS11 | B12: No | C12: missing pause/skip control | D12: zerodha varsity | E12: Sorry misspelled my name, its Mrinal 😅 ……….. And also one more query, i cannot place limit order on the ETFs in a Smallcase when I invest or do an SIP in it, so how do I go around that? | F12: no | G12: none | H12: none | I12: none | K12: yes | L12: |none| | M12: none | N12: |missing_control_pause_skip_modify| | O12: =IF(F12=K12,1,0) -> 0 | P12: =IF(OR(ISNUMBER(SEARCH("|"&G12&"|",L12)),AND(G12="none",OR(L12="|none|",L12=""))),1,0) -> 1 | Q12: =IF(H12=M12,1,0) -> 1 | R12: =IF(OR(ISNUMBER(SEARCH("|"&I12&"|",N12)),AND(I12="none",OR(N12="|none|",N12=""))),1,0) -> 0 | S12: pass
A13: GS12 | B13: No | C13: trust/support | D13: tradingqna | E13: @Bhuvan @Meher_Smaran @nithin Some help here will be appreciated, as Nippon is quick to completely shift the responsibility to Zerodha! | F13: no | G13: none | H13: none | I13: none | K13: yes | L13: |none| | M13: none | N13: |trust_or_support_failure| | O13: =IF(F13=K13,1,0) -> 0 | P13: =IF(OR(ISNUMBER(SEARCH("|"&G13&"|",L13)),AND(G13="none",OR(L13="|none|",L13=""))),1,0) -> 1 | Q13: =IF(H13=M13,1,0) -> 1 | R13: =IF(OR(ISNUMBER(SEARCH("|"&I13&"|",N13)),AND(I13="none",OR(N13="|none|",N13=""))),1,0) -> 0 | S13: pass
A14: GS13 | B14: No | C14: trust/support | D14: app store | E14: Application issue. I’m unable to open my portfolio.i want to close my all the investment,I’m very upset for your services,kindly help | F14: yes | G14: none | H14: voluntary | I14: app_friction_or_bug | K14: yes | L14: |redeemed_withdrew| | M14: voluntary | N14: |trust_or_support_failure|app_friction_or_bug| | O14: =IF(F14=K14,1,0) -> 1 | P14: =IF(OR(ISNUMBER(SEARCH("|"&G14&"|",L14)),AND(G14="none",OR(L14="|none|",L14=""))),1,0) -> 0 | Q14: =IF(H14=M14,1,0) -> 1 | R14: =IF(OR(ISNUMBER(SEARCH("|"&I14&"|",N14)),AND(I14="none",OR(N14="|none|",N14=""))),1,0) -> 1 | S14: pass
A15: GS14 | B15: No | C15: confusing numbers | D15: play store | E15: financial instrument's biggest asset is trust but this app has eroded my trust as the number shown in app for investment and gain/ loss is highly unreliable. In a recent incident, My invested value is shown reduced by 50k while I redeem 20k in total(which would have gain portion too). Despite writing to groww support that number shown in app is misleading and accurate. There is no response and action. is this technical issue or something fishi in groww which vanish hard earned money of investors | F15: yes | G15: stopped_cancelled | H15: voluntary | I15: confusing_numbers_or_terms | K15: yes | L15: |checked_tracked|redeemed_withdrew| | M15: none | N15: |confusing_numbers_or_terms|trust_or_support_failure| | O15: =IF(F15=K15,1,0) -> 1 | P15: =IF(OR(ISNUMBER(SEARCH("|"&G15&"|",L15)),AND(G15="none",OR(L15="|none|",L15=""))),1,0) -> 0 | Q15: =IF(H15=M15,1,0) -> 0 | R15: =IF(OR(ISNUMBER(SEARCH("|"&I15&"|",N15)),AND(I15="none",OR(N15="|none|",N15=""))),1,0) -> 1 | S15: pass
A16: GS15 | B16: No | C16: confusing numbers | D16: zerodha varsity | E16: Hello Sir, The SEBI 2017 circular mentions only Open-ended MF schemes. So, those guidelines are not applicable to closed-ended fund schemes? Thank you. | F16: no | G16: none | H16: none | I16: none | K16: yes | L16: |none| | M16: none | N16: |confusing_numbers_or_terms| | O16: =IF(F16=K16,1,0) -> 0 | P16: =IF(OR(ISNUMBER(SEARCH("|"&G16&"|",L16)),AND(G16="none",OR(L16="|none|",L16=""))),1,0) -> 1 | Q16: =IF(H16=M16,1,0) -> 1 | R16: =IF(OR(ISNUMBER(SEARCH("|"&I16&"|",N16)),AND(I16="none",OR(N16="|none|",N16=""))),1,0) -> 0 | S16: pass
A17: GS16 | B17: No | C17: returns / volatility | D17: tradingqna | E17: @mns2611 better to lose ourselves rather than another guy play and lose for us Recent DHFL default has affected many fund houses from UTI to DSP. I dont think debt funds or arbitrage fund etc has a reasonable promise even compared to equity funds promise Anycase i accept my knowledge in MF space is zero | F17: no | G17: none | H17: none | I17: none | K17: yes | L17: |none| | M17: none | N17: |negative_or_volatile_returns| | O17: =IF(F17=K17,1,0) -> 0 | P17: =IF(OR(ISNUMBER(SEARCH("|"&G17&"|",L17)),AND(G17="none",OR(L17="|none|",L17=""))),1,0) -> 1 | Q17: =IF(H17=M17,1,0) -> 1 | R17: =IF(OR(ISNUMBER(SEARCH("|"&I17&"|",N17)),AND(I17="none",OR(N17="|none|",N17=""))),1,0) -> 0 | S17: pass
A18: GS17 | B18: No | C18: returns / volatility | D18: play store | E18: I did the mistake of using this platform for my mutual fund purchases. They are completely unreliable as they can even make the unit purchases against your order on the next day even when you make the payment with partner bank before 2pm. This has caused a loss to me multiple times as the market condition changed due to volatility. | F18: yes | G18: continued | H18: none | I18: app_friction_or_bug | K18: yes | L18: |none| | M18: none | N18: |app_friction_or_bug|negative_or_volatile_returns| | O18: =IF(F18=K18,1,0) -> 1 | P18: =IF(OR(ISNUMBER(SEARCH("|"&G18&"|",L18)),AND(G18="none",OR(L18="|none|",L18=""))),1,0) -> 0 | Q18: =IF(H18=M18,1,0) -> 1 | R18: =IF(OR(ISNUMBER(SEARCH("|"&I18&"|",N18)),AND(I18="none",OR(N18="|none|",N18=""))),1,0) -> 1 | S18: pass
A19: GS18 | B19: No | C19: cashflow / emergency | D19: tradingqna | E19: The only caveat is that many times some extra cash is available in the trading account but not in the bank account… so I would have to wait for redemption proceeds to initiate purchases in new MF… | F19: no | G19: none | H19: none | I19: none | K19: yes | L19: |none| | M19: none | N19: |cashflow_or_income_change| | O19: =IF(F19=K19,1,0) -> 0 | P19: =IF(OR(ISNUMBER(SEARCH("|"&G19&"|",L19)),AND(G19="none",OR(L19="|none|",L19=""))),1,0) -> 1 | Q19: =IF(H19=M19,1,0) -> 1 | R19: =IF(OR(ISNUMBER(SEARCH("|"&I19&"|",N19)),AND(I19="none",OR(N19="|none|",N19=""))),1,0) -> 0 | S19: pass
A20: GS19 | B20: No | C20: cashflow / emergency | D20: play store | E20: I had withdrawn my investment in mutual funds a week ago. The app said the fund will be credited within 5 days. But i still didn't get the amount credited. When I tried to chat with their assistant boat. It doesn't reply properly. Hence I tried to mail them my issue. So i asked for customer care email id. But im not able to write them. The email wasn't supposed to be open for us. Even though my amount was small, it was important for me in this tough time. And this happened to me. | F20: yes | G20: stopped_cancelled | H20: voluntary | I20: none | K20: yes | L20: |redeemed_withdrew| | M20: none | N20: |emergency_or_goal_need_for_money|trust_or_support_failure| | O20: =IF(F20=K20,1,0) -> 1 | P20: =IF(OR(ISNUMBER(SEARCH("|"&G20&"|",L20)),AND(G20="none",OR(L20="|none|",L20=""))),1,0) -> 0 | Q20: =IF(H20=M20,1,0) -> 0 | R20: =IF(OR(ISNUMBER(SEARCH("|"&I20&"|",N20)),AND(I20="none",OR(N20="|none|",N20=""))),1,0) -> 0 | S20: pass
... A28: GS27 | B28: No | C28: GUARDRAIL: asks what to buy/stop | D28: tradingqna | E28: People often recommend investing in low cost passive funds to achieve financial freedom and build wealth. However, this process can take at least 15-20 years. In the meantime, where should one invest for short-term goals? What kind portfolio is suitable for this to achieve this? | F28: no | G28: none | H28: none | I28: none | K28: yes | L28: |none| | M28: none | N28: |none| | O28: =IF(F28=K28,1,0) -> 0 | P28: =IF(OR(ISNUMBER(SEARCH("|"&G28&"|",L28)),AND(G28="none",OR(L28="|none|",L28=""))),1,0) -> 1 | Q28: =IF(H28=M28,1,0) -> 1 | R28: =IF(OR(ISNUMBER(SEARCH("|"&I28&"|",N28)),AND(I28="none",OR(N28="|none|",N28=""))),1,0) -> 1 | S28: pass

Sheet Disagreements
A1: ID | B1: Source | C1: Fields that differ | D1: Analyst diagnosis (Claude's reading; the labeller's labels are unchanged)
A2: GS04 | B2: app store | C2: event | D2: Event: two readings fit. Labeller: payment failed/lapsed; AI: skipped. The writer says the instalment did not process, which matches 'payment failed' more closely.
A3: GS05 | B3: play store | C3: drop-off | D3: Drop-off: labeller None, AI Involuntary. The second instalment was rejected after deduction; whether one rejected instalment counts as a drop-off is a definition boundary.
A4: GS06 | B4: tradingqna | C4: relevant, event, drop-off, reason | D4: Relevance: a staff or forum reply explaining why orders fail, not the writer's own SIP experience. AI over-included forum replies.
A5: GS07 | B5: play store | C5: event, drop-off | D5: Event and drop-off: the writer asks for features before starting (labeller note: acquisition failed, nothing started). AI read it as a stop. AI over-read an event.
A6: GS08 | B6: app store | C6: reason | D6: Reason: labeller chose no clear reason; AI tagged app friction and trust/support for a cancellation that does not go through. Both defensible; the comment names an app failure.
A7: GS09 | B7: tradingqna | C7: relevant, event, drop-off, reason | D7: Relevance: general educational advice from a forum reply, not the writer's own SIP. AI over-included forum replies.
A8: GS10 | B8: play store | C8: event | D8: Event: labeller chose switched platform (the writer compares with Zerodha); AI found no event. The writer asks for a feature and mentions a competitor; no switch is stated.
A9: GS11 | B9: zerodha varsity | C9: relevant, reason | D9: Relevance: a query about limit orders on ETFs in a smallcase, not a mutual fund SIP experience. AI over-included.
A10: GS12 | B10: tradingqna | C10: relevant, reason | D10: Relevance: a forum tag asking staff for help, no SIP content in the text itself. AI over-included.
A11: GS13 | B11: app store | C11: event | D11: Event: labeller None, AI redeemed/withdrew. The writer wants to close all investments but has not yet; AI tagged an intention as an event.
A12: GS14 | B12: play store | C12: event, drop-off | D12: Event and drop-off: labeller stopped (voluntary); AI checked/redeemed with no drop-off. The writer describes lost trust in the numbers; a stop is implied, not stated.
... A24: GS27 | B24: tradingqna | C24: relevant | D24: Relevance: labeller No; AI Yes. A general question about where to invest for short-term goals, posted on a forum; a generic advice question. Definition boundary.

Sheet Robustness
A1: Source set | B1: Drop-off comments | C1: Involuntary (not their choice) | D1: Involuntary share | E1: Top reasons in drop-offs
A2: All sources | B2: 3336 | C2: 963 | D2: =C2/B2 -> 0.28866906 | E2: App bug/friction 26.3%, trust/support 21.6%, payment/mandate failure 17.8%
A3: Excluding TradingQnA and Zerodha Varsity | B3: 3011 | C3: 869 | D3: =C3/B3 -> 0.28860844 | E3: App bug/friction 26.6%, trust/support 23.2%, payment/mandate failure 18.2%
A4: App stores and Reddit only | B4: 2689 | C4: 773 | D4: =C4/B4 -> 0.28746746 | E4: App bug/friction 28.2%, trust/support 25.5%, payment/mandate failure 17.9%
A6: Source: counts from the engine's tagged corpus (21,445 relevant comments), computed 31 Oct 2026 with the engine's counting tools.
